follower_github/__init__.py
follower_github/api.py
follower_github-0.1.0.dist-info/LICENSE
follower_github-0.1.0.dist-info/METADATA
follower_github-0.1.0.dist-info/WHEEL
follower_github-0.1.0.dist-info/top_level.txt
follower_github-0.1.0.dist-info/RECORD
