Metadata-Version: 2.2
Name: follower_github
Version: 0.1.0
Summary: Uma biblioteca para listar seguidores ou perfis seguidos no GitHub.
Author-email: Ricardo7c <ricardo7c@hotmail.com>
License: MIT License
Requires-Python: >=3.7
License-File: LICENSE
Requires-Dist: requests>=2.31.0
Requires-Dist: urllib3>=1.26.0
